dwtest/__init__.py
dwtest/dwtest.py
dwtest-0.0.4.dist-info/LICENSE
dwtest-0.0.4.dist-info/METADATA
dwtest-0.0.4.dist-info/WHEEL
dwtest-0.0.4.dist-info/top_level.txt
dwtest-0.0.4.dist-info/RECORD
