Metadata-Version: 2.1
Name: dwtest
Version: 0.0.4
Summary: Durbin-Watson Test
Home-page: https://github.com/JackywithaWhiteDog/dwtest.git
Author: JackywithaWhiteDog
Author-email: jackyliu0129@gmail.com
License: UNKNOWN
Platform: UNKNOWN
Classifier: Programming Language :: Python :: 3
Classifier: License :: OSI Approved :: MIT License
Classifier: Operating System :: OS Independent
Requires-Python: >=3.6
